vizkit/__init__.py
vizkit/api/__init__.py
vizkit/api/api.py
vizkit/api/v1/__init__.py
vizkit/main.py
vizkit/pipeline/__init__.py
vizkit/pipeline/blocks/__init__.py
vizkit/pipeline/blocks/data_blocks.py
vizkit/pipeline/blocks/graph_blocks.py
vizkit/pipeline/data_files.py
vizkit/pipeline/data_source/__init__.py
vizkit/pipeline/data_source/firebase/__init__.py
vizkit/pipeline/data_source/firebase/app.py
vizkit/pipeline/data_source/firebase/auth.py
vizkit/pipeline/data_source/firebase/db.py
vizkit/pipeline/data_source/firebase/user.py
vizkit/pipeline/data_source/local/__init__.py
vizkit/pipeline/data_source/local/running_ng_loader.py
vizkit/pipeline/data_source/local/simple_loader.py
vizkit/pipeline/pipeline.py
vizkit/pipeline/serialize.py
vizkit/pipeline/utils.py
vizkit/web/components/block_controls.py
vizkit/web/components/filters.py
vizkit/web/components/flex.py
vizkit/web/components/footer.py
vizkit/web/plot.py
vizkit-0.0.2.dist-info/METADATA
vizkit-0.0.2.dist-info/WHEEL
vizkit-0.0.2.dist-info/entry_points.txt
vizkit-0.0.2.dist-info/RECORD
