Metadata-Version: 2.1
Name: vizkit
Version: 0.0.2
Summary: 
License: MIT
Author: Wenyu Zhao
Author-email: wenyuzhaox@gmail.com
Requires-Python: >=3.12,<4.0
Classifier: License :: OSI Approved :: MIT License
Classifier: Programming Language :: Python :: 3
Classifier: Programming Language :: Python :: 3.12
Requires-Dist: firebase-admin (>=6.5.0,<7.0.0)
Requires-Dist: pandas (>=2.2.2,<3.0.0)
Requires-Dist: scipy (>=1.14.1,<2.0.0)
Requires-Dist: shortuuid (>=1.0.13,<2.0.0)
Requires-Dist: streamlit (>=1.38.0,<2.0.0)
Requires-Dist: streamlit-js-eval (>=0.1.7,<0.2.0)
Requires-Dist: streamlit-oauth (>=0.1.13,<0.2.0)
Requires-Dist: streamlit-tree-select2 (>=0.0.7,<0.0.8)
Requires-Dist: watchdog (>=4.0.0,<5.0.0)
